setup.cfg
setup.py
mtkparse/__init__.py
mtkparse/mtkparse.py
mtkparse.egg-info/PKG-INFO
mtkparse.egg-info/SOURCES.txt
mtkparse.egg-info/dependency_links.txt
mtkparse.egg-info/not-zip-safe
mtkparse.egg-info/requires.txt
mtkparse.egg-info/top_level.txt