Metadata-Version: 2.1
Name: mtkparse
Version: 0.0.1
Summary: Parse module from motarik
Home-page: UNKNOWN
Author-email: shmelewm85@gmail.com
License: UNKNOWN
Platform: UNKNOWN
